LICENSE
MANIFEST.in
README.md
pyproject.toml
setup.py
robotransforms/__init__.py
robotransforms/_version.py
robotransforms/types.h
robotransforms.egg-info/PKG-INFO
robotransforms.egg-info/SOURCES.txt
robotransforms.egg-info/dependency_links.txt
robotransforms.egg-info/requires.txt
robotransforms.egg-info/top_level.txt
robotransforms/dead_reckon/__init__.py
robotransforms/dead_reckon/base.cpp
robotransforms/dead_reckon/base.h
robotransforms/dead_reckon/dead_reckon.py
robotransforms/dead_reckon/dead_reckon_pure.py
robotransforms/dead_reckon/wrapper.cpp
robotransforms/euclidean/__init__.py
robotransforms/euclidean/base.cpp
robotransforms/euclidean/base.h
robotransforms/euclidean/euclidean.py
robotransforms/euclidean/euclidean_pure.py
robotransforms/euclidean/wrapper.cpp
robotransforms/utils/__init__.py
robotransforms/utils/base.cpp
robotransforms/utils/base.h
robotransforms/utils/utils.py
robotransforms/utils/utils_pure.py
robotransforms/utils/wrapper.cpp