Metadata-Version: 2.4
Name: robotransforms
Version: 0.6.0
Summary: A transformation library for robot motion
Home-page: https://github.com/Nova-Dynamics/transforms-python
Author: Jonathan D. B. Van Schenck
Author-email: jvschenck@novadynamics.com
License: MIT
License-File: LICENSE
Requires-Dist: numpy>=1.19
Dynamic: author
Dynamic: author-email
Dynamic: description
Dynamic: description-content-type
Dynamic: home-page
Dynamic: license
Dynamic: license-file
Dynamic: requires-dist
Dynamic: summary
